LICENSE
MANIFEST.in
README.rst
setup.cfg
setup.py
./pandoc-source-exec.py
./pandoc_source_exec.py
pandoc_source_exec.egg-info/PKG-INFO
pandoc_source_exec.egg-info/SOURCES.txt
pandoc_source_exec.egg-info/dependency_links.txt
pandoc_source_exec.egg-info/entry_points.txt
pandoc_source_exec.egg-info/requires.txt
pandoc_source_exec.egg-info/top_level.txt