Metadata-Version: 1.1
Name: pandoc-source-exec
Version: 0.2.1
Summary: A pandoc filter for executing (python) code and including the results.
Home-page: https://github.com/shoeffner/pandoc-source-exec
Author: Sebastian Höffner
Author-email: info@sebastian-hoeffner.de
License: MIT
Download-URL: https://github.com/shoeffner/pandoc-source-exec/tarball/0.2.1
Keywords: pandoc,filter,code,execution
Platform: UNKNOWN
Classifier: Development Status :: 4 - Beta
Classifier: Intended Audience :: Science/Research
Classifier: License :: OSI Approved :: MIT License
Classifier: Natural Language :: English
Classifier: Programming Language :: Python :: 3.6
Classifier: Topic :: Text Processing :: Filters
